gambit_sdk/__init__.py
gambit_sdk/base_adapter/__init__.py
gambit_sdk/base_adapter/base_adapter.py
gambit_sdk/enums/__init__.py
gambit_sdk/enums/exercise_type_enum.py
gambit_sdk/schemas/__init__.py
gambit_sdk/schemas/exercise_structure_schemas.py
gambit_sdk/schemas/solution_type_schemas.py
gambit_sdk/schemas/unified_assignment_schemas.py
gambit_sdk/schemas/unified_exercise_schema.py
gambit_sdk/schemas/unified_grade_schema.py
gambit_sdk/schemas/unified_solution_schema.py
gambit_sdk-0.1.1.dist-info/METADATA
gambit_sdk-0.1.1.dist-info/WHEEL
gambit_sdk-0.1.1.dist-info/licenses/LICENSE
gambit_sdk-0.1.1.dist-info/RECORD
