Metadata-Version: 2.4
Name: gambit-sdk
Version: 0.1.1
Summary: The official SDK for building Gambit Platform Adapters
License: Proprietary
License-File: LICENSE
Keywords: sdk,api,gambit,edtech
Author: Mikhail Shevernev
Author-email: shevernev007@gmail.com
Requires-Python: >=3.13,<4.0
Classifier: Development Status :: 3 - Alpha
Classifier: Intended Audience :: Developers
Classifier: License :: Other/Proprietary License
Classifier: Operating System :: OS Independent
Classifier: Programming Language :: Python :: 3
Classifier: Programming Language :: Python :: 3.13
Classifier: Programming Language :: Python :: 3.14
Classifier: Topic :: Software Development :: Libraries :: Python Modules
Requires-Dist: httpx (>=0.28.1,<0.29.0)
Requires-Dist: pydantic (>=2.12.4,<3.0.0)
Requires-Dist: pydantic-settings (>=2.12.0,<3.0.0)
Project-URL: Homepage, https://github.com/brilliant-gambit/gambit-sdk
Project-URL: Repository, https://github.com/твой_ник/gambit-sdk
